[
    {
      "id": 1,
      "job_tag": "Software Developer",
      "skill_set": ["Java", "Python", "C++"],
      "work_period": "3 months",
      "budget_des": "Hourly",
      "budget": "$50 - $75 per hour",
      "job_des": "We are looking for a software developer who can work on multiple projects and write clean, maintainable, and efficient code.",
      "created_at":"2023-05-02T18:43:29.000000Z",
      "updated_at":"2023-05-05T12:32:06.000000Z"
    },
    {
      "id": 2,
      "job_tag": "UX Designer",
      "skill_set": ["Adobe XD", "Figma", "Sketch"],
      "work_period": "6 months",
      "budget_des": "Fixed",
      "budget": "$10,000 - $15,000",
      "job_des": "We are seeking a UX designer who can create visually appealing and user-friendly designs for web and mobile applications.",
      "created_at":"2023-04-17T09:52:59.000000Z",
      "updated_at":"2023-05-05T12:32:06.000000Z"
    },
    {
        "id": 0,
        "job_tag": "Software Developer",
        "skill_set": ["Java", "Python", "C++"],
        "work_period": "3 months",
        "budget_des": "Hourly",
        "budget": "$50 - $75 per hour",
        "job_des": "We are looking for a software developer who can work on multiple projects and write clean, maintainable, and efficient code.",
        "created_at":"2023-06-28T22:07:03.000000Z",
        "updated_at":"2023-05-05T12:32:06.000000Z"
      },
    {
      "id": 3,
      "job_tag": "Data Analyst",
      "skill_set": ["SQL", "Python", "Excel"],
      "work_period": "4 months",
      "budget_des": "Monthly",
      "budget": "$4,000 - $6,000 per month",
      "job_des": "We are looking for a data analyst who can perform complex data analysis and generate reports for our clients.",
      "created_at":"2023-05-05T12:32:06.000000Z",
      "updated_at":"2023-05-05T12:32:06.000000Z"
    },
    {
      "id": 4,
      "job_tag": "Social Media Manager",
      "skill_set": ["Facebook Ads", "Instagram Marketing", "Content Creation"],
      "work_period": "12 months",
      "budget_des": "Weekly",
      "budget": "$500 - $750 per week",
      "job_des": "We are seeking a social media manager who can manage and grow our social media presence across multiple platforms.",
      "created_at":"2023-10-11T02:15:44.000000Z",
      "updated_at":"2023-05-05T12:32:06.000000Z"
    },
    {
      "id": 5,
      "job_tag": "Sales Representative",
      "skill_set": ["Customer Relationship Management", "Salesforce", "Negotiation"],
      "work_period": "Indefinite",
      "budget_des": "Commission",
      "budget": "10% commission on sales",
      "job_des": "We are looking for a sales representative who can bring in new clients and increase our sales revenue.",
      "created_at":"2023-11-25T19:10:37.000000Z",
      "updated_at":"2023-05-05T12:32:06.000000Z"
    },
    {
      "id": 6,
      "job_tag": "Graphic Designer",
      "skill_set": ["Photoshop", "Illustrator", "InDesign"],
      "work_period": "2 months",
      "budget_des": "Fixed",
      "budget": "$5,000 - $7,500",
      "job_des": "We are seeking a graphic designer who can create visually stunning graphics and illustrations for our marketing campaigns.",
      "created_at":"2023-09-06T15:36:28.000000Z",
      "updated_at":"2023-05-05T12:32:06.000000Z"
    },
    {
      "id": 7,
      "job_tag": "Content Writer",
      "skill_set": ["SEO", "Copywriting", "Blogging"],
      "work_period": "6 months",
      "budget_des": "Monthly",
      "budget": "$3,000 - $5,000 per month",
      "job_des": "We are looking for a content writer who can write high-quality, engaging, and SEO-friendly content for our blog and website.",
      "created_at":"2023-07-05T13:21:48.000000Z",
      "updated_at":"2023-05-05T12:32:06.000000Z"
    },

    {"id":8,"job_tag":"Software Engineer",
    "skill_set": ["Java", "Python", "C++"],
    "work_period":"Medium",
    "budget_des":"Hourly rate",
    "budget":"100",
    "job_des":"We are seeking a highly experienced and skilled Senior Software Developer to join our dynamic team. The successful candidate will have a proven track record in designing and developing software solutions, as well as a strong understanding of programming principles and best practices. The role will involve working collaboratively with other developers, project managers, and stakeholders to design and implement high-quality software solutions.",
    "created_at":"2023-02-14T06:27:51.000000Z",
    "updated_at":"2023-05-05T12:32:06.000000Z"},

    {"id":9,"job_tag":"Testing Engineer",
    "skill_set": ["Java", "Python", "C++"],
    "work_period":"small",
    "budget_des":"Hourly rate",
    "budget":"5600-100,000",
    "job_des":"Looking for someone to build a single page app for me",
    "created_at":"2023-05-05T12:32:06.000000Z",
    "updated_at":"2023-05-05T12:32:06.000000Z"},

    {"id":10,"job_tag":"Color Artist",
    "skill_set": ["Java", "Python", "C++"],
    "work_period":"large",
    "budget_des":"Hourly rate",
    "budget":"1200",
    "job_des":"We are seeking a highly experienced and skilled Senior Software Developer to join our dynamic team. The successful candidate will have a proven track record in designing and developing software solutions, as well as a strong understanding of programming principles and best practices. The role will involve working collaboratively with other developers, project managers, and stakeholders to design and implement high-quality software solutions.",
    "created_at":"2023-05-05T12:32:06.000000Z",
    "updated_at":"2023-05-05T12:32:06.000000Z"}
]